cloud_storage_size/__init__.py
cloud_storage_size/gs_query_metrics.py
cloud_storage_size/pkg_util.py
cloud_storage_size/rclone.py
cloud_storage_size/rclone_test.py
cloud_storage_size/rclone_util.py
cloud_storage_size/sdk_client.py
cloud_storage_size-0.1.10.dist-info/METADATA
cloud_storage_size-0.1.10.dist-info/WHEEL
cloud_storage_size-0.1.10.dist-info/RECORD
