Metadata-Version: 2.1
Name: cloud-storage-size
Version: 0.1.10
Summary: A cloud storage file count & file size query library
Home-page: https://github.com/yingca1
Author: Ying Cai
Author-email: i@caiying.me
Requires-Python: >=3.10,<4.0
Classifier: Programming Language :: Python :: 3
Classifier: Programming Language :: Python :: 3.10
Classifier: Programming Language :: Python :: 3.11
Classifier: Programming Language :: Python :: 3.12
